rake_new2/__init__.py
rake_new2/__main__.py
rake_new2/rake_new2.py
rake_new2-1.0.5.dist-info/LICENSE.txt
rake_new2-1.0.5.dist-info/METADATA
rake_new2-1.0.5.dist-info/WHEEL
rake_new2-1.0.5.dist-info/top_level.txt
rake_new2-1.0.5.dist-info/RECORD
