Metadata-Version: 2.1
Name: rake-new2
Version: 1.0.5
Summary: A Python library that enables smooth keyword extraction from any text using the RAKE(Rapid Automatic Keyword Extraction) algorithm.
Home-page: https://github.com/BALaka-18/rake_new2
Author: Balaka Biswas
Author-email: balaka2605@gmail.com
License: MIT
Platform: UNKNOWN
Classifier: License :: OSI Approved :: MIT License
Classifier: Programming Language :: Python :: 3
Classifier: Programming Language :: Python :: 3.5
Classifier: Programming Language :: Python :: 3.6
Classifier: Programming Language :: Python :: 3.7
Classifier: Operating System :: OS Independent
Requires-Python: >=3.6
Requires-Dist: nltk
